pyobfuscator/__init__.py
pyobfuscator/cli.py
pyobfuscator/core.py
pyobfuscator/gui.py
pyobfuscator/encoders/__init__.py
pyobfuscator/encoders/base.py
pyobfuscator/encoders/dna_encoder.py
pyobfuscator/encoders/fast_encoders.py
pyobfuscator/encoders/fractal_encoder.py
pyobfuscator/encoders/neural_encoder.py
pyobfuscator/encoders/quantum_encoder.py
pyobfuscator/encoders/runtime_reconstructor.py
pyobfuscator/encoders/simple_encoder.py
pyobfuscator/encoders/steganographic_encoder.py
pyobfuscator/encoders/tensor_encoder.py
pyobfuscator_advanced-1.0.0.dist-info/METADATA
pyobfuscator_advanced-1.0.0.dist-info/WHEEL
pyobfuscator_advanced-1.0.0.dist-info/entry_points.txt
pyobfuscator_advanced-1.0.0.dist-info/top_level.txt
pyobfuscator_advanced-1.0.0.dist-info/RECORD
