Metadata-Version: 2.4
Name: pyobfuscator-advanced
Version: 1.0.0
Summary: Advanced Python code obfuscation library with novel encoding techniques
Home-page: https://pypi.org/project/pyobfuscator-advanced/
Author: PyObfuscator Team
Author-email: zinzied@gmail.com
Project-URL: Homepage, https://pypi.org/project/pyobfuscator-advanced/
Project-URL: Documentation, https://pypi.org/project/pyobfuscator-advanced/
Keywords: obfuscation,code protection,encryption,security,python
Classifier: Development Status :: 5 - Production/Stable
Classifier: Intended Audience :: Developers
Classifier: Topic :: Software Development :: Libraries :: Python Modules
Classifier: Topic :: Security :: Cryptography
Classifier: License :: OSI Approved :: MIT License
Classifier: Programming Language :: Python :: 3
Classifier: Programming Language :: Python :: 3.8
Classifier: Programming Language :: Python :: 3.9
Classifier: Programming Language :: Python :: 3.10
Classifier: Programming Language :: Python :: 3.11
Classifier: Programming Language :: Python :: 3.12
Classifier: Operating System :: OS Independent
Requires-Python: >=3.8
Requires-Dist: numpy>=1.21.0
Requires-Dist: PyQt6>=6.4.0
Requires-Dist: astor>=0.8.1
Requires-Dist: pytest>=7.0.0
Requires-Dist: pytest-cov>=4.0.0
Requires-Dist: pyinstaller>=5.0.0
Requires-Dist: scipy>=1.9.0
Provides-Extra: gui
Requires-Dist: PyQt6>=6.4.0; extra == "gui"
Provides-Extra: dev
Requires-Dist: pytest>=7.0.0; extra == "dev"
Requires-Dist: pytest-cov>=4.0.0; extra == "dev"
Dynamic: author
Dynamic: author-email
Dynamic: classifier
Dynamic: description
Dynamic: description-content-type
Dynamic: home-page
Dynamic: keywords
Dynamic: project-url
Dynamic: provides-extra
Dynamic: requires-dist
Dynamic: requires-python
Dynamic: summary
